{
  "total": {
    "deliveries": 2469,
    "hu": 3104,
    "lines": 3076,
    "lines_picked": 1537,
    "lines_not_picked": 1539,
    "qty": 8542,
    "percentage_picked": 49.97
  },
  "by_date": [
    {
      "date": "2025-02-18",
      "stats": {
        "deliveries": 1,
        "hu": 2,
        "lines": 2,
        "lines_picked": 2,
        "lines_not_picked": 0,
        "qty": 10,
        "by_status": {
          "C": {
            "deliveries": 1,
            "hu": 2,
            "lines": 2,
            "lines_picked": 2,
            "lines_not_picked": 0,
            "qty": 10,
            "percentage_picked": 100.0
          }
        },
        "by_process": {
          "P2B": {
            "deliveries": 1,
            "hu": 2,
            "lines": 2,
            "lines_picked": 2,
            "lines_not_picked": 0,
            "qty": 10,
            "percentage_picked": 100.0
          }
        },
        "by_nesting": {
          "false": {
            "deliveries": 1,
            "hu": 2,
            "lines": 2,
            "lines_picked": 2,
            "lines_not_picked": 0,
            "qty": 10,
            "percentage_picked": 100.0
          }
        },
        "by_cons": {
          "true": {
            "deliveries": 1,
            "hu": 2,
            "lines": 2,
            "lines_picked": 2,
            "lines_not_picked": 0,
            "qty": 10,
            "percentage_picked": 100.0
          }
        },
        "by_gi_time": {
          "18:29:59": {
            "deliveries": 1,
            "hu": 2,
            "lines": 2,
            "lines_picked": 2,
            "lines_not_picked": 0,
            "qty": 10,
            "percentage_picked": 100.0
          }
        },
        "by_vas": {
          "False": {
            "deliveries": 1,
            "hu": 2,
            "lines": 2,
            "lines_picked": 2,
            "lines_not_picked": 0,
            "qty": 10,
            "percentage_picked": 100.0
          }
        },
        "by_dg_vas": {
          "False": {
            "deliveries": 1,
            "hu": 2,
            "lines": 2,
            "lines_picked": 2,
            "lines_not_picked": 0,
            "qty": 10,
            "percentage_picked": 100.0
          }
        },
        "percentage_picked": 100.0
      }
    },
    {
      "date": "2025-04-22",
      "stats": {
        "deliveries": 629,
        "hu": 778,
        "lines": 917,
        "lines_picked": 549,
        "lines_not_picked": 368,
        "qty": 3103,
        "by_status": {
          "B": {
            "deliveries": 269,
            "hu": 363,
            "lines": 478,
            "lines_picked": 117,
            "lines_not_picked": 361,
            "qty": 1941,
            "percentage_picked": 24.48
          },
          "A": {
            "deliveries": 77,
            "hu": 97,
            "lines": 7,
            "lines_picked": 0,
            "lines_not_picked": 7,
            "qty": 13,
            "percentage_picked": 0.0
          },
          "C": {
            "deliveries": 283,
            "hu": 318,
            "lines": 432,
            "lines_picked": 432,
            "lines_not_picked": 0,
            "qty": 1149,
            "percentage_picked": 100.0
          }
        },
        "by_process": {
          "P2B": {
            "deliveries": 628,
            "hu": 778,
            "lines": 909,
            "lines_picked": 549,
            "lines_not_picked": 360,
            "qty": 3103,
            "percentage_picked": 60.4
          },
          "LEGACY": {
            "deliveries": 1,
            "hu": 0,
            "lines": 8,
            "lines_picked": 0,
            "lines_not_picked": 8,
            "qty": 0,
            "percentage_picked": 0.0
          }
        },
        "by_nesting": {
          "false": {
            "deliveries": 621,
            "hu": 727,
            "lines": 769,
            "lines_picked": 408,
            "lines_not_picked": 361,
            "qty": 2489,
            "percentage_picked": 53.06
          },
          "true": {
            "deliveries": 8,
            "hu": 51,
            "lines": 148,
            "lines_picked": 141,
            "lines_not_picked": 7,
            "qty": 614,
            "percentage_picked": 95.27
          }
        },
        "by_cons": {
          "false": {
            "deliveries": 590,
            "hu": 626,
            "lines": 647,
            "lines_picked": 356,
            "lines_not_picked": 291,
            "qty": 2144,
            "percentage_picked": 55.02
          },
          "true": {
            "deliveries": 39,
            "hu": 152,
            "lines": 270,
            "lines_picked": 193,
            "lines_not_picked": 77,
            "qty": 959,
            "percentage_picked": 71.48
          }
        },
        "by_gi_time": {
          "10:12:23": {
            "deliveries": 1,
            "hu": 1,
            "lines": 1,
            "lines_picked": 0,
            "lines_not_picked": 1,
            "qty": 3,
            "percentage_picked": 0.0
          },
          "12:59:59": {
            "deliveries": 2,
            "hu": 2,
            "lines": 1,
            "lines_picked": 0,
            "lines_not_picked": 1,
            "qty": 3,
            "percentage_picked": 0.0
          },
          "15:59:59": {
            "deliveries": 29,
            "hu": 32,
            "lines": 39,
            "lines_picked": 28,
            "lines_not_picked": 11,
            "qty": 54,
            "percentage_picked": 71.79
          },
          "16:29:59": {
            "deliveries": 7,
            "hu": 13,
            "lines": 25,
            "lines_picked": 10,
            "lines_not_picked": 15,
            "qty": 52,
            "percentage_picked": 40.0
          },
          "16:59:59": {
            "deliveries": 3,
            "hu": 3,
            "lines": 3,
            "lines_picked": 1,
            "lines_not_picked": 2,
            "qty": 10,
            "percentage_picked": 33.33
          },
          "17:59:59": {
            "deliveries": 96,
            "hu": 138,
            "lines": 155,
            "lines_picked": 70,
            "lines_not_picked": 85,
            "qty": 853,
            "percentage_picked": 45.16
          },
          "18:29:59": {
            "deliveries": 3,
            "hu": 3,
            "lines": 2,
            "lines_picked": 2,
            "lines_not_picked": 0,
            "qty": 2,
            "percentage_picked": 100.0
          },
          "18:59:59": {
            "deliveries": 102,
            "hu": 109,
            "lines": 164,
            "lines_picked": 128,
            "lines_not_picked": 36,
            "qty": 359,
            "percentage_picked": 78.05
          },
          "19:29:59": {
            "deliveries": 64,
            "hu": 122,
            "lines": 142,
            "lines_picked": 91,
            "lines_not_picked": 51,
            "qty": 636,
            "percentage_picked": 64.08
          },
          "20:29:59": {
            "deliveries": 5,
            "hu": 9,
            "lines": 10,
            "lines_picked": 5,
            "lines_not_picked": 5,
            "qty": 13,
            "percentage_picked": 50.0
          },
          "20:59:59": {
            "deliveries": 309,
            "hu": 336,
            "lines": 352,
            "lines_picked": 205,
            "lines_not_picked": 147,
            "qty": 1054,
            "percentage_picked": 58.24
          },
          "22:59:59": {
            "deliveries": 8,
            "hu": 10,
            "lines": 23,
            "lines_picked": 9,
            "lines_not_picked": 14,
            "qty": 64,
            "percentage_picked": 39.13
          }
        },
        "by_vas": {
          "False": {
            "deliveries": 608,
            "hu": 740,
            "lines": 872,
            "lines_picked": 515,
            "lines_not_picked": 357,
            "qty": 2988,
            "percentage_picked": 59.06
          },
          "True": {
            "deliveries": 21,
            "hu": 38,
            "lines": 45,
            "lines_picked": 34,
            "lines_not_picked": 11,
            "qty": 115,
            "percentage_picked": 75.56
          }
        },
        "by_dg_vas": {
          "False": {
            "deliveries": 617,
            "hu": 765,
            "lines": 901,
            "lines_picked": 538,
            "lines_not_picked": 363,
            "qty": 3087,
            "percentage_picked": 59.71
          },
          "True": {
            "deliveries": 12,
            "hu": 13,
            "lines": 16,
            "lines_picked": 11,
            "lines_not_picked": 5,
            "qty": 16,
            "percentage_picked": 68.75
          }
        },
        "percentage_picked": 59.87
      }
    },
    {
      "date": "2025-04-23",
      "stats": {
        "deliveries": 1546,
        "hu": 2001,
        "lines": 1938,
        "lines_picked": 955,
        "lines_not_picked": 983,
        "qty": 4627,
        "by_status": {
          "C": {
            "deliveries": 605,
            "hu": 624,
            "lines": 854,
            "lines_picked": 854,
            "lines_not_picked": 0,
            "qty": 2303,
            "percentage_picked": 100.0
          },
          "A": {
            "deliveries": 346,
            "hu": 640,
            "lines": 0,
            "lines_picked": 0,
            "lines_not_picked": 0,
            "qty": 0,
            "percentage_picked": 0
          },
          "B": {
            "deliveries": 595,
            "hu": 737,
            "lines": 1084,
            "lines_picked": 101,
            "lines_not_picked": 983,
            "qty": 2324,
            "percentage_picked": 9.32
          }
        },
        "by_process": {
          "P2B": {
            "deliveries": 1546,
            "hu": 2001,
            "lines": 1938,
            "lines_picked": 955,
            "lines_not_picked": 983,
            "qty": 4627,
            "percentage_picked": 49.28
          }
        },
        "by_nesting": {
          "false": {
            "deliveries": 1543,
            "hu": 1967,
            "lines": 1896,
            "lines_picked": 917,
            "lines_not_picked": 979,
            "qty": 4544,
            "percentage_picked": 48.36
          },
          "true": {
            "deliveries": 3,
            "hu": 34,
            "lines": 42,
            "lines_picked": 38,
            "lines_not_picked": 4,
            "qty": 83,
            "percentage_picked": 90.48
          }
        },
        "by_cons": {
          "true": {
            "deliveries": 57,
            "hu": 218,
            "lines": 299,
            "lines_picked": 105,
            "lines_not_picked": 194,
            "qty": 889,
            "percentage_picked": 35.12
          },
          "false": {
            "deliveries": 1489,
            "hu": 1783,
            "lines": 1639,
            "lines_picked": 850,
            "lines_not_picked": 789,
            "qty": 3738,
            "percentage_picked": 51.86
          }
        },
        "by_gi_time": {
          "04:00:01": {
            "deliveries": 3,
            "hu": 4,
            "lines": 6,
            "lines_picked": 6,
            "lines_not_picked": 0,
            "qty": 6,
            "percentage_picked": 100.0
          },
          "08:00:01": {
            "deliveries": 1,
            "hu": 1,
            "lines": 0,
            "lines_picked": 0,
            "lines_not_picked": 0,
            "qty": 0,
            "percentage_picked": 0
          },
          "12:59:59": {
            "deliveries": 4,
            "hu": 19,
            "lines": 43,
            "lines_picked": 21,
            "lines_not_picked": 22,
            "qty": 166,
            "percentage_picked": 48.84
          },
          "13:59:59": {
            "deliveries": 7,
            "hu": 14,
            "lines": 8,
            "lines_picked": 2,
            "lines_not_picked": 6,
            "qty": 20,
            "percentage_picked": 25.0
          },
          "15:59:59": {
            "deliveries": 152,
            "hu": 196,
            "lines": 151,
            "lines_picked": 60,
            "lines_not_picked": 91,
            "qty": 266,
            "percentage_picked": 39.74
          },
          "16:29:59": {
            "deliveries": 69,
            "hu": 198,
            "lines": 71,
            "lines_picked": 25,
            "lines_not_picked": 46,
            "qty": 185,
            "percentage_picked": 35.21
          },
          "16:59:59": {
            "deliveries": 11,
            "hu": 13,
            "lines": 10,
            "lines_picked": 3,
            "lines_not_picked": 7,
            "qty": 11,
            "percentage_picked": 30.0
          },
          "17:59:59": {
            "deliveries": 59,
            "hu": 100,
            "lines": 100,
            "lines_picked": 61,
            "lines_not_picked": 39,
            "qty": 232,
            "percentage_picked": 61.0
          },
          "18:29:59": {
            "deliveries": 1,
            "hu": 1,
            "lines": 0,
            "lines_picked": 0,
            "lines_not_picked": 0,
            "qty": 0,
            "percentage_picked": 0
          },
          "18:59:59": {
            "deliveries": 456,
            "hu": 480,
            "lines": 589,
            "lines_picked": 340,
            "lines_not_picked": 249,
            "qty": 1302,
            "percentage_picked": 57.72
          },
          "19:29:59": {
            "deliveries": 182,
            "hu": 293,
            "lines": 266,
            "lines_picked": 132,
            "lines_not_picked": 134,
            "qty": 724,
            "percentage_picked": 49.62
          },
          "20:59:59": {
            "deliveries": 584,
            "hu": 605,
            "lines": 678,
            "lines_picked": 295,
            "lines_not_picked": 383,
            "qty": 1680,
            "percentage_picked": 43.51
          },
          "22:59:59": {
            "deliveries": 17,
            "hu": 77,
            "lines": 16,
            "lines_picked": 10,
            "lines_not_picked": 6,
            "qty": 35,
            "percentage_picked": 62.5
          }
        },
        "by_vas": {
          "False": {
            "deliveries": 1471,
            "hu": 1914,
            "lines": 1772,
            "lines_picked": 900,
            "lines_not_picked": 872,
            "qty": 4398,
            "percentage_picked": 50.79
          },
          "True": {
            "deliveries": 75,
            "hu": 87,
            "lines": 166,
            "lines_picked": 55,
            "lines_not_picked": 111,
            "qty": 229,
            "percentage_picked": 33.13
          }
        },
        "by_dg_vas": {
          "False": {
            "deliveries": 1512,
            "hu": 1961,
            "lines": 1801,
            "lines_picked": 922,
            "lines_not_picked": 879,
            "qty": 4481,
            "percentage_picked": 51.19
          },
          "True": {
            "deliveries": 34,
            "hu": 40,
            "lines": 137,
            "lines_picked": 33,
            "lines_not_picked": 104,
            "qty": 146,
            "percentage_picked": 24.09
          }
        },
        "percentage_picked": 49.28
      }
    },
    {
      "date": "2025-04-24",
      "stats": {
        "deliveries": 127,
        "hu": 179,
        "lines": 129,
        "lines_picked": 19,
        "lines_not_picked": 110,
        "qty": 373,
        "by_status": {
          "B": {
            "deliveries": 69,
            "hu": 84,
            "lines": 118,
            "lines_picked": 8,
            "lines_not_picked": 110,
            "qty": 348,
            "percentage_picked": 6.78
          },
          "A": {
            "deliveries": 48,
            "hu": 85,
            "lines": 0,
            "lines_picked": 0,
            "lines_not_picked": 0,
            "qty": 0,
            "percentage_picked": 0
          },
          "C": {
            "deliveries": 10,
            "hu": 10,
            "lines": 11,
            "lines_picked": 11,
            "lines_not_picked": 0,
            "qty": 25,
            "percentage_picked": 100.0
          }
        },
        "by_process": {
          "P2B": {
            "deliveries": 127,
            "hu": 179,
            "lines": 129,
            "lines_picked": 19,
            "lines_not_picked": 110,
            "qty": 373,
            "percentage_picked": 14.73
          }
        },
        "by_nesting": {
          "false": {
            "deliveries": 127,
            "hu": 179,
            "lines": 129,
            "lines_picked": 19,
            "lines_not_picked": 110,
            "qty": 373,
            "percentage_picked": 14.73
          }
        },
        "by_cons": {
          "false": {
            "deliveries": 121,
            "hu": 158,
            "lines": 103,
            "lines_picked": 16,
            "lines_not_picked": 87,
            "qty": 295,
            "percentage_picked": 15.53
          },
          "true": {
            "deliveries": 6,
            "hu": 21,
            "lines": 26,
            "lines_picked": 3,
            "lines_not_picked": 23,
            "qty": 78,
            "percentage_picked": 11.54
          }
        },
        "by_gi_time": {
          "00:00:00": {
            "deliveries": 4,
            "hu": 4,
            "lines": 4,
            "lines_picked": 0,
            "lines_not_picked": 4,
            "qty": 28,
            "percentage_picked": 0.0
          },
          "12:59:59": {
            "deliveries": 1,
            "hu": 5,
            "lines": 5,
            "lines_picked": 0,
            "lines_not_picked": 5,
            "qty": 35,
            "percentage_picked": 0.0
          },
          "15:59:59": {
            "deliveries": 7,
            "hu": 7,
            "lines": 4,
            "lines_picked": 0,
            "lines_not_picked": 4,
            "qty": 11,
            "percentage_picked": 0.0
          },
          "16:29:59": {
            "deliveries": 7,
            "hu": 11,
            "lines": 11,
            "lines_picked": 0,
            "lines_not_picked": 11,
            "qty": 19,
            "percentage_picked": 0.0
          },
          "16:59:59": {
            "deliveries": 1,
            "hu": 1,
            "lines": 1,
            "lines_picked": 0,
            "lines_not_picked": 1,
            "qty": 2,
            "percentage_picked": 0.0
          },
          "17:59:59": {
            "deliveries": 5,
            "hu": 5,
            "lines": 5,
            "lines_picked": 0,
            "lines_not_picked": 5,
            "qty": 41,
            "percentage_picked": 0.0
          },
          "18:59:59": {
            "deliveries": 25,
            "hu": 25,
            "lines": 23,
            "lines_picked": 5,
            "lines_not_picked": 18,
            "qty": 40,
            "percentage_picked": 21.74
          },
          "19:29:59": {
            "deliveries": 24,
            "hu": 62,
            "lines": 28,
            "lines_picked": 4,
            "lines_not_picked": 24,
            "qty": 69,
            "percentage_picked": 14.29
          },
          "20:59:59": {
            "deliveries": 49,
            "hu": 54,
            "lines": 46,
            "lines_picked": 9,
            "lines_not_picked": 37,
            "qty": 124,
            "percentage_picked": 19.57
          },
          "22:59:59": {
            "deliveries": 2,
            "hu": 3,
            "lines": 1,
            "lines_picked": 1,
            "lines_not_picked": 0,
            "qty": 2,
            "percentage_picked": 100.0
          },
          "23:59:00": {
            "deliveries": 2,
            "hu": 2,
            "lines": 1,
            "lines_picked": 0,
            "lines_not_picked": 1,
            "qty": 2,
            "percentage_picked": 0.0
          }
        },
        "by_vas": {
          "False": {
            "deliveries": 122,
            "hu": 169,
            "lines": 111,
            "lines_picked": 17,
            "lines_not_picked": 94,
            "qty": 342,
            "percentage_picked": 15.32
          },
          "True": {
            "deliveries": 5,
            "hu": 10,
            "lines": 18,
            "lines_picked": 2,
            "lines_not_picked": 16,
            "qty": 31,
            "percentage_picked": 11.11
          }
        },
        "by_dg_vas": {
          "False": {
            "deliveries": 122,
            "hu": 173,
            "lines": 118,
            "lines_picked": 17,
            "lines_not_picked": 101,
            "qty": 352,
            "percentage_picked": 14.41
          },
          "True": {
            "deliveries": 5,
            "hu": 6,
            "lines": 11,
            "lines_picked": 2,
            "lines_not_picked": 9,
            "qty": 21,
            "percentage_picked": 18.18
          }
        },
        "percentage_picked": 14.73
      }
    },
    {
      "date": "2025-04-25",
      "stats": {
        "deliveries": 128,
        "hu": 136,
        "lines": 82,
        "lines_picked": 12,
        "lines_not_picked": 70,
        "qty": 384,
        "by_status": {
          "B": {
            "deliveries": 64,
            "hu": 65,
            "lines": 71,
            "lines_picked": 1,
            "lines_not_picked": 70,
            "qty": 323,
            "percentage_picked": 1.41
          },
          "A": {
            "deliveries": 56,
            "hu": 63,
            "lines": 0,
            "lines_picked": 0,
            "lines_not_picked": 0,
            "qty": 0,
            "percentage_picked": 0
          },
          "C": {
            "deliveries": 8,
            "hu": 8,
            "lines": 11,
            "lines_picked": 11,
            "lines_not_picked": 0,
            "qty": 61,
            "percentage_picked": 100.0
          }
        },
        "by_process": {
          "P2B": {
            "deliveries": 128,
            "hu": 136,
            "lines": 82,
            "lines_picked": 12,
            "lines_not_picked": 70,
            "qty": 384,
            "percentage_picked": 14.63
          }
        },
        "by_nesting": {
          "false": {
            "deliveries": 128,
            "hu": 136,
            "lines": 82,
            "lines_picked": 12,
            "lines_not_picked": 70,
            "qty": 384,
            "percentage_picked": 14.63
          }
        },
        "by_cons": {
          "false": {
            "deliveries": 127,
            "hu": 134,
            "lines": 80,
            "lines_picked": 12,
            "lines_not_picked": 68,
            "qty": 382,
            "percentage_picked": 15.0
          },
          "true": {
            "deliveries": 1,
            "hu": 2,
            "lines": 2,
            "lines_picked": 0,
            "lines_not_picked": 2,
            "qty": 2,
            "percentage_picked": 0.0
          }
        },
        "by_gi_time": {
          "15:59:59": {
            "deliveries": 5,
            "hu": 5,
            "lines": 2,
            "lines_picked": 0,
            "lines_not_picked": 2,
            "qty": 16,
            "percentage_picked": 0.0
          },
          "16:29:59": {
            "deliveries": 8,
            "hu": 14,
            "lines": 3,
            "lines_picked": 0,
            "lines_not_picked": 3,
            "qty": 5,
            "percentage_picked": 0.0
          },
          "17:59:59": {
            "deliveries": 3,
            "hu": 4,
            "lines": 2,
            "lines_picked": 0,
            "lines_not_picked": 2,
            "qty": 2,
            "percentage_picked": 0.0
          },
          "18:29:59": {
            "deliveries": 4,
            "hu": 4,
            "lines": 4,
            "lines_picked": 0,
            "lines_not_picked": 4,
            "qty": 8,
            "percentage_picked": 0.0
          },
          "18:59:59": {
            "deliveries": 17,
            "hu": 18,
            "lines": 13,
            "lines_picked": 8,
            "lines_not_picked": 5,
            "qty": 65,
            "percentage_picked": 61.54
          },
          "19:29:59": {
            "deliveries": 7,
            "hu": 7,
            "lines": 5,
            "lines_picked": 0,
            "lines_not_picked": 5,
            "qty": 9,
            "percentage_picked": 0.0
          },
          "20:59:59": {
            "deliveries": 42,
            "hu": 42,
            "lines": 25,
            "lines_picked": 3,
            "lines_not_picked": 22,
            "qty": 104,
            "percentage_picked": 12.0
          },
          "22:59:59": {
            "deliveries": 1,
            "hu": 1,
            "lines": 0,
            "lines_picked": 0,
            "lines_not_picked": 0,
            "qty": 0,
            "percentage_picked": 0
          },
          "23:59:58": {
            "deliveries": 41,
            "hu": 41,
            "lines": 28,
            "lines_picked": 1,
            "lines_not_picked": 27,
            "qty": 175,
            "percentage_picked": 3.57
          }
        },
        "by_vas": {
          "False": {
            "deliveries": 119,
            "hu": 127,
            "lines": 70,
            "lines_picked": 12,
            "lines_not_picked": 58,
            "qty": 366,
            "percentage_picked": 17.14
          },
          "True": {
            "deliveries": 9,
            "hu": 9,
            "lines": 12,
            "lines_picked": 0,
            "lines_not_picked": 12,
            "qty": 18,
            "percentage_picked": 0.0
          }
        },
        "by_dg_vas": {
          "False": {
            "deliveries": 128,
            "hu": 136,
            "lines": 82,
            "lines_picked": 12,
            "lines_not_picked": 70,
            "qty": 384,
            "percentage_picked": 14.63
          }
        },
        "percentage_picked": 14.63
      }
    },
    {
      "date": "2025-04-28",
      "stats": {
        "deliveries": 2,
        "hu": 2,
        "lines": 2,
        "lines_picked": 0,
        "lines_not_picked": 2,
        "qty": 2,
        "by_status": {
          "B": {
            "deliveries": 2,
            "hu": 2,
            "lines": 2,
            "lines_picked": 0,
            "lines_not_picked": 2,
            "qty": 2,
            "percentage_picked": 0.0
          }
        },
        "by_process": {
          "P2B": {
            "deliveries": 2,
            "hu": 2,
            "lines": 2,
            "lines_picked": 0,
            "lines_not_picked": 2,
            "qty": 2,
            "percentage_picked": 0.0
          }
        },
        "by_nesting": {
          "false": {
            "deliveries": 2,
            "hu": 2,
            "lines": 2,
            "lines_picked": 0,
            "lines_not_picked": 2,
            "qty": 2,
            "percentage_picked": 0.0
          }
        },
        "by_cons": {
          "false": {
            "deliveries": 2,
            "hu": 2,
            "lines": 2,
            "lines_picked": 0,
            "lines_not_picked": 2,
            "qty": 2,
            "percentage_picked": 0.0
          }
        },
        "by_gi_time": {
          "16:29:59": {
            "deliveries": 2,
            "hu": 2,
            "lines": 2,
            "lines_picked": 0,
            "lines_not_picked": 2,
            "qty": 2,
            "percentage_picked": 0.0
          }
        },
        "by_vas": {
          "True": {
            "deliveries": 2,
            "hu": 2,
            "lines": 2,
            "lines_picked": 0,
            "lines_not_picked": 2,
            "qty": 2,
            "percentage_picked": 0.0
          }
        },
        "by_dg_vas": {
          "False": {
            "deliveries": 2,
            "hu": 2,
            "lines": 2,
            "lines_picked": 0,
            "lines_not_picked": 2,
            "qty": 2,
            "percentage_picked": 0.0
          }
        },
        "percentage_picked": 0.0
      }
    },
    {
      "date": "2025-04-29",
      "stats": {
        "deliveries": 6,
        "hu": 6,
        "lines": 6,
        "lines_picked": 0,
        "lines_not_picked": 6,
        "qty": 43,
        "by_status": {
          "B": {
            "deliveries": 6,
            "hu": 6,
            "lines": 6,
            "lines_picked": 0,
            "lines_not_picked": 6,
            "qty": 43,
            "percentage_picked": 0.0
          }
        },
        "by_process": {
          "P2B": {
            "deliveries": 6,
            "hu": 6,
            "lines": 6,
            "lines_picked": 0,
            "lines_not_picked": 6,
            "qty": 43,
            "percentage_picked": 0.0
          }
        },
        "by_nesting": {
          "false": {
            "deliveries": 6,
            "hu": 6,
            "lines": 6,
            "lines_picked": 0,
            "lines_not_picked": 6,
            "qty": 43,
            "percentage_picked": 0.0
          }
        },
        "by_cons": {
          "false": {
            "deliveries": 6,
            "hu": 6,
            "lines": 6,
            "lines_picked": 0,
            "lines_not_picked": 6,
            "qty": 43,
            "percentage_picked": 0.0
          }
        },
        "by_gi_time": {
          "20:59:59": {
            "deliveries": 6,
            "hu": 6,
            "lines": 6,
            "lines_picked": 0,
            "lines_not_picked": 6,
            "qty": 43,
            "percentage_picked": 0.0
          }
        },
        "by_vas": {
          "False": {
            "deliveries": 6,
            "hu": 6,
            "lines": 6,
            "lines_picked": 0,
            "lines_not_picked": 6,
            "qty": 43,
            "percentage_picked": 0.0
          }
        },
        "by_dg_vas": {
          "False": {
            "deliveries": 6,
            "hu": 6,
            "lines": 6,
            "lines_picked": 0,
            "lines_not_picked": 6,
            "qty": 43,
            "percentage_picked": 0.0
          }
        },
        "percentage_picked": 0.0
      }
    },
    {
      "date": "No Date",
      "stats": {
        "deliveries": 30,
        "hu": 0,
        "lines": 0,
        "lines_picked": 0,
        "lines_not_picked": 0,
        "qty": 0,
        "by_status": {
          "C": {
            "deliveries": 29,
            "hu": 0,
            "lines": 0,
            "lines_picked": 0,
            "lines_not_picked": 0,
            "qty": 0,
            "percentage_picked": 0
          },
          "B": {
            "deliveries": 1,
            "hu": 0,
            "lines": 0,
            "lines_picked": 0,
            "lines_not_picked": 0,
            "qty": 0,
            "percentage_picked": 0
          }
        },
        "by_process": {
          "": {
            "deliveries": 30,
            "hu": 0,
            "lines": 0,
            "lines_picked": 0,
            "lines_not_picked": 0,
            "qty": 0,
            "percentage_picked": 0
          }
        },
        "by_nesting": {
          "": {
            "deliveries": 30,
            "hu": 0,
            "lines": 0,
            "lines_picked": 0,
            "lines_not_picked": 0,
            "qty": 0,
            "percentage_picked": 0
          }
        },
        "by_cons": {
          "": {
            "deliveries": 30,
            "hu": 0,
            "lines": 0,
            "lines_picked": 0,
            "lines_not_picked": 0,
            "qty": 0,
            "percentage_picked": 0
          }
        },
        "by_gi_time": {
          "": {
            "deliveries": 30,
            "hu": 0,
            "lines": 0,
            "lines_picked": 0,
            "lines_not_picked": 0,
            "qty": 0,
            "percentage_picked": 0
          }
        },
        "by_vas": {
          "False": {
            "deliveries": 30,
            "hu": 0,
            "lines": 0,
            "lines_picked": 0,
            "lines_not_picked": 0,
            "qty": 0,
            "percentage_picked": 0
          }
        },
        "by_dg_vas": {
          "False": {
            "deliveries": 30,
            "hu": 0,
            "lines": 0,
            "lines_picked": 0,
            "lines_not_picked": 0,
            "qty": 0,
            "percentage_picked": 0
          }
        },
        "percentage_picked": 0
      }
    }
  ]
}